qcsc_mod/__init__.py
qcsc_mod/actions.py
qcsc_mod/content_ai.py
qcsc_mod/image_ai.py
qcsc_mod/main.py
qcsc_mod-0.1.0.dist-info/licenses/LICENSE
qcsc_mod-0.1.0.dist-info/METADATA
qcsc_mod-0.1.0.dist-info/WHEEL
qcsc_mod-0.1.0.dist-info/top_level.txt
qcsc_mod-0.1.0.dist-info/RECORD
