Metadata-Version: 2.4
Name: qcsc-mod
Version: 0.1.0
Summary: A Universal Content & Action Orchestrator leveraging AI for content creation and automation.
Author-email: Your Name <your.email@example.com>
Project-URL: Homepage, https://github.com/yourusername/qcsc-mod
Project-URL: Bug Tracker, https://github.com/yourusername/qcsc-mod/issues
Keywords: ai,llm,content-generation,automation,text-processing,image-generation,orchestration,utility
Classifier: Programming Language :: Python :: 3
Classifier: License :: OSI Approved :: MIT License
Classifier: Operating System :: OS Independent
Classifier: Development Status :: 3 - Alpha
Classifier: Intended Audience :: Developers
Classifier: Intended Audience :: End Users/Desktop
Classifier: Topic :: Scientific/Engineering :: Artificial Intelligence
Classifier: Topic :: Text Processing
Classifier: Topic :: Utilities
Requires-Python: >=3.8
License-File: LICENSE
Requires-Dist: requests
Requires-Dist: Pillow
Provides-Extra: dev
Requires-Dist: pytest>=7.0; extra == "dev"
Requires-Dist: flake8; extra == "dev"
Requires-Dist: black; extra == "dev"
Dynamic: license-file
